protofy/__init__.py
protofy/auth.py
protofy/events.py
protofy/agent/ProtoAgentsInterface.py
protofy/agent/ProtoMqttAgent.py
protofy/agent/__init__.py
protofy/agent/bifrost.py
protofy-0.1.4.dist-info/METADATA
protofy-0.1.4.dist-info/WHEEL
protofy-0.1.4.dist-info/top_level.txt
protofy-0.1.4.dist-info/RECORD
