Metadata-Version: 2.1
Name: protofy
Version: 0.1.4
Summary: UNKNOWN
Home-page: UNKNOWN
License: UNKNOWN
Platform: UNKNOWN
Requires-Dist: paho-mqtt>=2.1.0
Requires-Dist: requests>=2.32.3
